pyquanttrade/Policy.py
pyquanttrade/__init__.py
pyquanttrade/market.py
pyquanttrade/engine/__init__.py
pyquanttrade/engine/commands.py
pyquanttrade/engine/test_result.py
pyquanttrade/engine/test_summary.py
pyquanttrade/engine/trade.py
pyquanttrade/engine/utils.py
pyquanttrade/engine/stats/__init__.py
pyquanttrade/engine/stats/daily_stats.py
pyquanttrade/engine/stats/summary_stats.py
pyquanttrade/engine/stats/trade_stats.py
pyquanttrade/features/__init__.py
pyquanttrade/features/functions.py
pyquanttrade/features/indicators.py
pyquanttrade-0.0.2.dist-info/LICENSE
pyquanttrade-0.0.2.dist-info/METADATA
pyquanttrade-0.0.2.dist-info/WHEEL
pyquanttrade-0.0.2.dist-info/top_level.txt
pyquanttrade-0.0.2.dist-info/RECORD
